j5gerggnpuiwerbngpiutbgn0iutb0p/__init__.py
j5gerggnpuiwerbngpiutbgn0iutb0p-0.0.1.dist-info/METADATA
j5gerggnpuiwerbngpiutbgn0iutb0p-0.0.1.dist-info/WHEEL
j5gerggnpuiwerbngpiutbgn0iutb0p-0.0.1.dist-info/top_level.txt
j5gerggnpuiwerbngpiutbgn0iutb0p-0.0.1.dist-info/RECORD
